.gitignore
CHANGES.rst
README.rst
setup.py
docs/.gitignore
docs/Makefile
docs/conf.py
docs/index.rst
docs/make.bat
octomotron/__init__.py
octomotron/approve.py
octomotron/bases.py
octomotron/deploy.py
octomotron/example.py
octomotron/exc.py
octomotron/harness.py
octomotron/main.py
octomotron/remove.py
octomotron/serve.py
octomotron/update.py
octomotron/utils.py
octomotron.egg-info/PKG-INFO
octomotron.egg-info/SOURCES.txt
octomotron.egg-info/dependency_links.txt
octomotron.egg-info/entry_points.txt
octomotron.egg-info/not-zip-safe
octomotron.egg-info/requires.txt
octomotron.egg-info/top_level.txt
octomotron/buildout_ext/setup.py
octomotron/buildout_ext/octomotron_buildout/__init__.py
octomotron/examples/buildout/README.txt
octomotron/examples/buildout/bootstrap.py
octomotron/examples/buildout/buildout.cfg
octomotron/examples/buildout/etc/octomotron.ini
octomotron/examples/buildout/surebro_octomotron/setup.py
octomotron/examples/buildout/surebro_octomotron/surebro_octomotron/__init__.py
octomotron/examples/buildout/surebro_octomotron/surebro_octomotron/__build__/bootstrap.py
octomotron/examples/buildout/surebro_octomotron/surebro_octomotron/__build__/buildout.cfg
octomotron/examples/buildout/surebro_octomotron/surebro_octomotron/__build__/etc/supervisord.conf.tmpl
octomotron/examples/buildout/surebro_octomotron/surebro_octomotron/__build__/etc/surebro.ini.tmpl
octomotron/examples/buildout/surebro_octomotron/surebro_octomotron/__build__/etc/zeo.conf.tmpl
octomotron/examples/virtualenv/README.txt
octomotron/examples/virtualenv/requirements.txt
octomotron/examples/virtualenv/setup.py
octomotron/examples/virtualenv/etc/octomotron.ini
octomotron/examples/virtualenv/surebro_octomotron/__init__.py
octomotron/examples/virtualenv/surebro_octomotron/__build__/requirements.txt
octomotron/examples/virtualenv/surebro_octomotron/__build__/etc/supervisord.conf.tmpl
octomotron/examples/virtualenv/surebro_octomotron/__build__/etc/surebro.ini.tmpl
octomotron/examples/virtualenv/surebro_octomotron/__build__/etc/zeo.conf.tmpl
octomotron/tests/__init__.py
octomotron/tests/test_functional.py
octomotron/webui/__init__.py
octomotron/webui/application.py
octomotron/webui/auth.py
octomotron/webui/htpasswd.py
