Metadata-Version: 1.1
Name: octomotron
Version: 0.2
Summary: A tool for rapid deployment of multiple evluation copies of a web application based on different git branches.
Home-page: http://pylonsproject.org
Author: Chris Rossi
Author-email: pylons-devel@googlegroups.com
License: BSD-derived (http://www.repoze.org/LICENSE.txt)
Keywords: web wsgi pylons
Platform: UNKNOWN
Classifier: Intended Audience :: Developers
Classifier: Programming Language :: Python
Classifier: Framework :: Pylons
Classifier: Topic :: Internet :: WWW/HTTP
Classifier: Topic :: Internet :: WWW/HTTP :: WSGI
Classifier: License :: Repoze Public License
